<?xml version="1.0" encoding="utf-8" ?><dwsync><file name="entity.inc" server="aps-dev1.com//" local="3486628588" remote="7781576596" Dst="-1" /><file name="node.inc" server="aps-dev1.com//" local="3486628588" remote="-4611698487525806188" Dst="-1" /><file name="node_add_form.inc" server="aps-dev1.com//" local="3486628588" remote="-4611698487525806188" Dst="-1" /><file name="node_edit_form.inc" server="aps-dev1.com//" local="3486628588" remote="-4611698487525806188" Dst="-1" /><file name="string.inc" server="aps-dev1.com//" local="3486628588" remote="-4611698487525806188" Dst="-1" /><file name="term.inc" server="aps-dev1.com//" local="3486628588" remote="-4611698487525806188" Dst="-1" /><file name="terms.inc" server="aps-dev1.com//" local="3486628588" remote="-4611698487525806188" Dst="-1" /><file name="user.inc" server="aps-dev1.com//" local="3486628588" remote="-4611698487525806188" Dst="-1" /><file name="token.inc" server="aps-dev1.com//" local="3486628588" remote="-4611698487525806188" Dst="-1" /><file name="user_edit_form.inc" server="aps-dev1.com//" local="3486628588" remote="-4611698487525806188" Dst="-1" /><file name="vocabulary.inc" server="aps-dev1.com//" local="3486628588" remote="-4611698487525806188" Dst="-1" /><file name="entity.inc" server="5.153.9.59" local="3492660782" remote="12082622972" Dst="-1" /><file name="node.inc" server="5.153.9.59" local="3492660782" remote="12082622972" Dst="-1" /><file name="node_add_form.inc" server="5.153.9.59" local="3492660782" remote="12082622972" Dst="-1" /><file name="node_edit_form.inc" server="5.153.9.59" local="3492660782" remote="12082622972" Dst="-1" /><file name="string.inc" server="5.153.9.59" local="3492660782" remote="12082622972" Dst="-1" /><file name="term.inc" server="5.153.9.59" local="3492660782" remote="12082622972" Dst="-1" /><file name="terms.inc" server="5.153.9.59" local="3492660782" remote="12082622972" Dst="-1" /><file name="token.inc" server="5.153.9.59" local="3492660782" remote="12082622972" Dst="-1" /><file name="user.inc" server="5.153.9.59" local="3492660782" remote="12082622972" Dst="-1" /><file name="user_edit_form.inc" server="5.153.9.59" local="3492660782" remote="12082622972" Dst="-1" /><file name="vocabulary.inc" server="5.153.9.59" local="3492660782" remote="12082622972" Dst="-1" /></dwsync>