<?xml version="1.0" encoding="utf-8" ?><dwsync><file name="API.txt" server="aps-dev1.com//" local="3486628641" remote="7781578876" Dst="-1" /><file name="INSTALL.txt" server="aps-dev1.com//" local="3486628640" remote="-4611698487525803908" Dst="-1" /><file name="LICENSE.txt" server="aps-dev1.com//" local="3486628641" remote="-4611698487525803908" Dst="-1" /><file name="pathauto.admin.inc" server="aps-dev1.com//" local="3486628640" remote="-4611698487525803908" Dst="-1" /><file name="pathauto.api.php" server="aps-dev1.com//" local="3486628641" remote="-4611698487525803908" Dst="-1" /><file name="pathauto.info" server="aps-dev1.com//" local="3486628640" remote="-4611698487525803908" Dst="-1" /><file name="pathauto.inc" server="aps-dev1.com//" local="3486628640" remote="-4611698487525803908" Dst="-1" /><file name="pathauto.install" server="aps-dev1.com//" local="3486628641" remote="-4611698487525803908" Dst="-1" /><file name="pathauto.js" server="aps-dev1.com//" local="3486628641" remote="-4611698487525803908" Dst="-1" /><file name="pathauto.module" server="aps-dev1.com//" local="3486628641" remote="-4611698487525803908" Dst="-1" /><file name="pathauto.pathauto.inc" server="aps-dev1.com//" local="3486628640" remote="-4611698487525803908" Dst="-1" /><file name="pathauto.test" server="aps-dev1.com//" local="3486628640" remote="-4611698487525803908" Dst="-1" /><file name="pathauto.tokens.inc" server="aps-dev1.com//" local="3486628641" remote="-4611698487525803908" Dst="-1" /><file name="README.txt" server="aps-dev1.com//" local="3486628640" remote="-4611698487525803908" Dst="-1" /><file name="API.txt" server="5.153.9.59" local="3492660782" remote="12082623152" Dst="-1" /><file name="INSTALL.txt" server="5.153.9.59" local="3492660782" remote="12082623152" Dst="-1" /><file name="LICENSE.txt" server="5.153.9.59" local="3492660782" remote="12082623152" Dst="-1" /><file name="pathauto.admin.inc" server="5.153.9.59" local="3492660782" remote="12082623152" Dst="-1" /><file name="pathauto.api.php" server="5.153.9.59" local="3492660782" remote="12082623152" Dst="-1" /><file name="pathauto.info" server="5.153.9.59" local="3492660782" remote="12082623152" Dst="-1" /><file name="pathauto.inc" server="5.153.9.59" local="3492660782" remote="12082623152" Dst="-1" /><file name="pathauto.install" server="5.153.9.59" local="3492660782" remote="12082623152" Dst="-1" /><file name="pathauto.js" server="5.153.9.59" local="3492660782" remote="12082623152" Dst="-1" /><file name="pathauto.module" server="5.153.9.59" local="3492660782" remote="12082623152" Dst="-1" /><file name="pathauto.pathauto.inc" server="5.153.9.59" local="3492660782" remote="12082623152" Dst="-1" /><file name="pathauto.test" server="5.153.9.59" local="3492660782" remote="12082623152" Dst="-1" /><file name="pathauto.tokens.inc" server="5.153.9.59" local="3492660782" remote="12082623152" Dst="-1" /><file name="README.txt" server="5.153.9.59" local="3492660782" remote="12082623152" Dst="-1" /></dwsync>